LICENSE
MANIFEST.in
README
setup.py
django_simple_utilities.egg-info/PKG-INFO
django_simple_utilities.egg-info/SOURCES.txt
django_simple_utilities.egg-info/dependency_links.txt
django_simple_utilities.egg-info/not-zip-safe
django_simple_utilities.egg-info/top_level.txt
utilities/__init__.py
utilities/csv_generator.py
utilities/deep_copy.py
utilities/models.py
utilities/relativedelta.py
utilities/utils.py
utilities/admin/__init__.py
utilities/admin/filters.py
utilities/admin/widgets.py
utilities/dashboard/__init__.py
utilities/forms/__init__.py
utilities/forms/validators.py
utilities/forms/widgets.py
utilities/localization/__init__.py
utilities/localization/decorators.py
utilities/localization/manager.py
utilities/models/__init__.py
utilities/models/fields.py
utilities/models/signals.py
utilities/static/utilities/admin/js/RelatedObjectLookups.js
utilities/static/utilities/admin/js/form-columns.js
utilities/static/utilities/admin/js/jquery.colorbox-min.js
utilities/static/utilities/admin/js/popup.js
utilities/static/utilities/js/jquery-1.6.4.min.js
utilities/static/utilities/js/forms/initial-form.js
utilities/static/utilities/js/models/fields.js
utilities/static/utilities/js/models/textareas.js
utilities/static/utilities/js/models/tinymce/changelog.txt
utilities/static/utilities/js/models/tinymce/examples/custom_formats.html
utilities/static/utilities/js/models/tinymce/examples/full.html
utilities/static/utilities/js/models/tinymce/examples/index.html
utilities/static/utilities/js/models/tinymce/examples/menu.html
utilities/static/utilities/js/models/tinymce/examples/simple.html
utilities/static/utilities/js/models/tinymce/examples/skins.html
utilities/static/utilities/js/models/tinymce/examples/translate.html
utilities/static/utilities/js/models/tinymce/examples/word.html
utilities/static/utilities/js/models/tinymce/examples/lists/image_list.js
utilities/static/utilities/js/models/tinymce/examples/lists/link_list.js
utilities/static/utilities/js/models/tinymce/examples/lists/media_list.js
utilities/static/utilities/js/models/tinymce/examples/lists/template_list.js
utilities/static/utilities/js/models/tinymce/jscripts/tiny_mce/license.txt
