Metadata-Version: 1.0
Name: django-simple-utilities
Version: 0.8
Summary: Simple utilities which help create django application.
Home-page: https://www.assembla.com/code/django-simple-utilities/git/nodes
Author: Lubos Matl
Author-email: matllubos@gmail.com
License: GPL
Keywords: django,admin,utilities
Platform: UNKNOWN
Classifier: Development Status :: 4 - Beta
Classifier: Environment :: Web Environment
Classifier: Framework :: Django
Classifier: Intended Audience :: Developers
Classifier: Intended Audience :: End Users/Desktop
Classifier: License :: OSI Approved :: GNU General Public License (GPL)
Classifier: Natural Language :: Czech
Classifier: Operating System :: OS Independent
Classifier: Programming Language :: Python
Classifier: Topic :: Internet :: WWW/HTTP :: Dynamic Content
Classifier: Topic :: Internet :: WWW/HTTP :: Site Management
